__init__.py
kak.py
skt.py
yaqq.py
yaqq_ds.py
yaqq_nus.py
yaqq-0.13.7.dist-info/COPYING
yaqq-0.13.7.dist-info/METADATA
yaqq-0.13.7.dist-info/WHEEL
yaqq-0.13.7.dist-info/top_level.txt
yaqq-0.13.7.dist-info/RECORD
