Metadata-Version: 2.1
Name: yaqq
Version: 0.13.7
Summary: Yet Another Quantum Quantizer - Design Space Exploration of Quantum Gate Sets using Novelty Search
Home-page: https://github.com/Advanced-Research-Centre/YAQQ
Author: Quantum Intelligence Research Group
License: AGPL v3
Project-URL: Source Code, https://github.com/Advanced-Research-Centre/YAQQ
Keywords: quantum compiler
Classifier: Environment :: Console
Classifier: License :: OSI Approved :: GNU Affero General Public License v3
Classifier: Intended Audience :: Developers
Classifier: Intended Audience :: Science/Research
Classifier: Operating System :: Microsoft :: Windows
Classifier: Programming Language :: Python :: 3 :: Only
Classifier: Programming Language :: Python :: 3.12
Classifier: Topic :: Scientific/Engineering
Requires-Python: >=3.12
License-File: COPYING
Requires-Dist: numpy >=1.26.4
Requires-Dist: qiskit >=1.2.4
Requires-Dist: astropy >=6.1.6
Requires-Dist: matplotlib >=3.9.2
Requires-Dist: scipy >=1.14.1
Requires-Dist: tqdm >=4.65.0
Requires-Dist: qutip >=5.0.4
Requires-Dist: scikit-learn >=1.5.2
Requires-Dist: weylchamber >=0.6.0
